trongridperm/__init__.py
trongridperm/main.py
trongridperm-0.0.1.dist-info/LICENSE.txt
trongridperm-0.0.1.dist-info/METADATA
trongridperm-0.0.1.dist-info/WHEEL
trongridperm-0.0.1.dist-info/top_level.txt
trongridperm-0.0.1.dist-info/RECORD
