Metadata-Version: 2.1
Name: trongridperm
Version: 0.0.1
Summary: trongridperm library for Python
Author: zinaron
Author-email: yadari1575@devdigs.com
License: MIT
Project-URL: Source Repository, https://github.com
License-File: LICENSE.txt
Requires-Dist: requests
